iconizer/__init__.py
iconizer/app_starter_example.py
iconizer/app_starter_script_example.py
iconizer/iconizer_app_root.py
iconizer/iconizer_app_root_v2.py
iconizer/iconizer_client.py
iconizer/iconizer_consts.py
iconizer/iconizer_main.py
iconizer/iconizer_server.py
iconizer/iconizer_task_config.py
iconizer/nameserver.py
iconizer/pyro_launcher.py
iconizer/pyro_service_base.py
iconizer/stoppable_thread.py
iconizer/utils.py
iconizer/console/__init__.py
iconizer/console/console_output_collector.py
iconizer/console/drop_wnd_handler.py
iconizer/console/drop_wnd_handler_v2.py
iconizer/console/gui_factory_base.py
iconizer/console/launcher.py
iconizer/console/msg_handler.py
iconizer/logsys/__init__.py
iconizer/logsys/libsys.py
iconizer/logsys/logDir.py
iconizer/logsys/logSys.py
iconizer/qtconsole/__init__.py
iconizer/qtconsole/browser.py
iconizer/qtconsole/droppable.py
iconizer/qtconsole/droppable.ui
iconizer/qtconsole/fileTools.py
iconizer/qtconsole/gf-16x16.png
iconizer/qtconsole/libsys.py
iconizer/qtconsole/list_window.py
iconizer/qtconsole/list_window.ui
iconizer/qtconsole/notification.py
iconizer/qtconsole/notification.ui
iconizer/qtconsole/pyqt_console_output_wnd.py
iconizer/qtconsole/pyqt_taskbar_icon.py
iconizer/qtconsole/pyqt_ui_backend.py
iconizer/win/__init__.py
iconizer/win/sysprocess.py
iconizer-0.1.5.dist-info/AUTHORS.rst
iconizer-0.1.5.dist-info/LICENSE
iconizer-0.1.5.dist-info/METADATA
iconizer-0.1.5.dist-info/WHEEL
iconizer-0.1.5.dist-info/top_level.txt
iconizer-0.1.5.dist-info/RECORD
