Metadata-Version: 2.1
Name: iconizer
Version: 0.1.5
Summary: "Iconize console application to task bar icon."
Home-page: https://github.com/weijia/iconizer
Author: Richard Wang
Author-email: richardwangwang@gmail.com
License: BSD
Keywords: iconizer
Classifier: Development Status :: 2 - Pre-Alpha
Classifier: Intended Audience :: Developers
Classifier: License :: OSI Approved :: BSD License
Classifier: Natural Language :: English
Classifier: Programming Language :: Python :: 2
Classifier: Programming Language :: Python :: 2.6
Classifier: Programming Language :: Python :: 2.7
Classifier: Programming Language :: Python :: 3
Classifier: Programming Language :: Python :: 3.3
License-File: LICENSE
License-File: AUTHORS.rst
